modsim/__init__.py
modsim/__main__.py
modsim/main.py
modsim/utils.py
modbus_tcp_simulator-0.5.0.dist-info/LICENSE
modbus_tcp_simulator-0.5.0.dist-info/METADATA
modbus_tcp_simulator-0.5.0.dist-info/WHEEL
modbus_tcp_simulator-0.5.0.dist-info/entry_points.txt
modbus_tcp_simulator-0.5.0.dist-info/RECORD
