Metadata-Version: 2.1
Name: modbus-tcp-simulator
Version: 0.5.0
Summary: A Simple Modbus TCP Device Simulator used for modpoll tool
Home-page: https://github.com/gavinying/modsim
Author: Ying Shaodong
Author-email: helloysd@gmail.com
Requires-Python: >=3.8.2,<4.0
Classifier: Programming Language :: Python :: 3
Classifier: Programming Language :: Python :: 3.9
Classifier: Programming Language :: Python :: 3.10
Classifier: Programming Language :: Python :: 3.11
Classifier: Programming Language :: Python :: 3.12
Requires-Dist: pymodbus (>=3.5.4,<3.6.0)
Project-URL: Documentation, https://gavinying.github.io/modsim/
Project-URL: Repository, https://github.com/gavinying/modsim
